commandLineMusicVideo/__init__.py
commandLineMusicVideo/__main__.py
commandLineMusicVideo-0.2.0.dist-info/LICENSE
commandLineMusicVideo-0.2.0.dist-info/METADATA
commandLineMusicVideo-0.2.0.dist-info/WHEEL
commandLineMusicVideo-0.2.0.dist-info/top_level.txt
commandLineMusicVideo-0.2.0.dist-info/RECORD
