Metadata-Version: 2.1
Name: commandLineMusicVideo
Version: 0.2.0
Summary: A small example package
Home-page: https://github.com/MartinBarker/commandLineMusicVideo
Author: Martin Barker
Author-email: martinbarker99@gmail.com
License: UNKNOWN
Platform: UNKNOWN
Classifier: Programming Language :: Python :: 3
Classifier: License :: OSI Approved :: MIT License
Classifier: Operating System :: OS Independent
Requires-Python: >=3.6
